{"entries": [{"type": "attribute", "name": "name", "desc": " Name of included module "}, {"type": "public class method", "name": "new(name, comment)", "desc": "Creates a new Mixin for name with comment"}, {"type": "public instance method", "name": "<=>(other)", "desc": "Mixins are sorted by name"}, {"type": "public instance method", "name": "full_name()", "desc": "Full name based on module"}, {"type": "public instance method", "name": "module()", "desc": "Attempts to locate the included module object.  Returns the name if not known."}, {"type": "public instance method", "name": "store=(store)", "desc": "Sets the store for this class or module and its contained code objects."}]}