{"entries": [{"type": "public class method", "name": "declare(test, repository)", "desc": "Executes a SpecFetcher setup block.  Yields an instance then creates the gems and specifications defined in the instance."}, {"type": "public instance method", "name": "created_specs()", "desc": "Returns a Hash of created Specification full names and the corresponding Specification."}, {"type": "public instance method", "name": "download(name, version, dependencies = nil, &block)", "desc": "Creates a gem with name, version and deps.  The created gem is downloaded in to the cache directory but is not installed"}, {"type": "public instance method", "name": "gem(name, version, dependencies = nil, &block)", "desc": "Creates a gem with name, version and deps.  The created gem can be downloaded and installed."}, {"type": "public instance method", "name": "legacy_platform()", "desc": "Creates a legacy platform spec with the name 'pl' and version 1"}, {"type": "public instance method", "name": "spec(name, version, dependencies = nil, &block)", "desc": "Creates a spec with name, version and deps.  The created gem can be downloaded and installed."}]}