{"entries": [{"type": "public class method", "name": "new()", "desc": ""}, {"type": "public instance method", "name": "execute()", "desc": ""}, {"type": "public instance method", "name": "rubygems_target_version()", "desc": ""}, {"type": "public instance method", "name": "update_gem(name, version = Gem::Requirement.default)", "desc": ""}, {"type": "public instance method", "name": "update_gems(gems_to_update)", "desc": ""}, {"type": "public instance method", "name": "update_rubygems()", "desc": "Update RubyGems software to the latest version."}, {"type": "public instance method", "name": "which_to_update(highest_installed_gems, gem_names, system = false)", "desc": ""}]}